.readthedocs.yaml
CHANGELOG.rst
CONTRIBUTING.rst
LICENSE.rst
MANIFEST.in
README.rst
pylama.ini
pyproject.toml
setup.cfg
setup.py
docs/api.rst
docs/changelog.rst
docs/conf.py
docs/convenience.rst
docs/errata.rst
docs/examples.rst
docs/glossary.rst
docs/index.rst
docs/_static/.gitinclude
docs/_templates/.gitinclude
src/processrunner/__init__.py
src/processrunner/classtemplate.py
src/processrunner/command.py
src/processrunner/commandmanager.py
src/processrunner/contentwrapper.py
src/processrunner/exceptionhandler.py
src/processrunner/kitchenpatch.py
src/processrunner/priterator.py
src/processrunner/processrunner.py
src/processrunner/prpipe.py
src/processrunner/prpipereader.py
src/processrunner/prpipewriter.py
src/processrunner/queuelink.py
src/processrunner/runcommand.py
src/processrunner/settings.py
src/processrunner/ssh.py
src/processrunner/timer.py
src/processrunner/version.py
src/processrunner/which.py
src/processrunner/writeout.py
src/processrunner.egg-info/PKG-INFO
src/processrunner.egg-info/SOURCES.txt
src/processrunner.egg-info/dependency_links.txt
src/processrunner.egg-info/requires.txt
src/processrunner.egg-info/top_level.txt