Metadata-Version: 2.1
Name: processrunner
Version: 2.6.0
Summary: Easily trigger and manage output from external processes.
Home-page: https://github.com/arobb/python-processrunner
Author: Andy Robb
Author-email: andy@andyrobb.com
License: MIT
Keywords: external process execution
Platform: UNKNOWN
Classifier: Development Status :: 4 - Beta
Classifier: Intended Audience :: Developers
Classifier: Topic :: Utilities
Classifier: License :: OSI Approved :: MIT License
Classifier: Operating System :: POSIX
Classifier: Programming Language :: Python :: 2
Classifier: Programming Language :: Python :: 2.7
Classifier: Programming Language :: Python :: 3
Classifier: Programming Language :: Python :: 3.7
Classifier: Programming Language :: Python :: 3.8
Classifier: Programming Language :: Python :: 3.9
Provides-Extra: dev
Provides-Extra: test
Provides-Extra: docs
